CYB600_Lab1_Huff4a-0.6.data/scripts/cyb600_lab1_server
csc_cyb600_huff4/__init__.py
csc_cyb600_huff4/time.py
CYB600_Lab1_Huff4a-0.6.dist-info/LICENSE
CYB600_Lab1_Huff4a-0.6.dist-info/METADATA
CYB600_Lab1_Huff4a-0.6.dist-info/WHEEL
CYB600_Lab1_Huff4a-0.6.dist-info/top_level.txt
CYB600_Lab1_Huff4a-0.6.dist-info/RECORD
