Metadata-Version: 2.1
Name: CYB600-Lab1-Huff4a
Version: 0.6
Classifier: Programming Language :: Python :: 3
Classifier: License :: OSI Approved :: MIT License
Classifier: Operating System :: OS Independent
License-File: LICENSE
Requires-Dist: Flask
